TBFLib/Main.py
TBFLib/__init__.py
TBFLib-1.2.dist-info/LICENSE
TBFLib-1.2.dist-info/METADATA
TBFLib-1.2.dist-info/WHEEL
TBFLib-1.2.dist-info/top_level.txt
TBFLib-1.2.dist-info/RECORD
