Metadata-Version: 2.1
Name: TBFLib
Version: 1.2
Summary: That's Formula module for python.
Author-email: fly-toribird <fly-toribird@outlook.com>
License: Apache License
Project-URL: Repository, https://github.com/fly-toribird/TBF
Classifier: Programming Language :: Python :: 3
Classifier: Topic :: Scientific/Engineering :: Mathematics
Requires-Python: >=3.8
License-File: LICENSE
